<dataStore>
  <id>DataStoreInfoImpl-4a3ced34:13835bab66a:-5be1</id>
  <name>DSEWPaC Key Ecological Features T East</name>
  <type>Shapefile</type>
  <enabled>true</enabled>
  <workspace>
    <id>WorkspaceInfoImpl-3b0a723a:137e9896802:-7ffe</id>
  </workspace>
  <connectionParameters>
    <entry key='memory mapped buffer'>false</entry>
    <entry key='create spatial index'>true</entry>
    <entry key='charset'>ISO-8859-1</entry>
    <entry key='filetype'>shapefile</entry>
    <entry key='cache and reuse memory maps'>true</entry>
    <entry key='url'>file:data/DSEWPAC_KEFs/te_kefs_2011.shp</entry>
    <entry key='namespace'>aodn</entry>
  </connectionParameters>
  <__default>false</__default>
</dataStore>
